pyautoattack/__init__.py
pyautoattack/autoattack.py
pyautoattack/autopgd_base.py
pyautoattack/checks.py
pyautoattack/fab_base.py
pyautoattack/fab_projections.py
pyautoattack/fab_pt.py
pyautoattack/fab_tf.py
pyautoattack/other_utils.py
pyautoattack/square.py
pyautoattack/state.py
pyautoattack/utils_tf.py
pyautoattack/utils_tf2.py
pyautoattack/examples/eval.py
pyautoattack/examples/eval_tf1.py
pyautoattack/examples/eval_tf2.py
pyautoattack/examples/model_test.pt
pyautoattack/examples/resnet.py
pyautoattack/examples/tf_model.weight.h5
pyautoattack-0.2.0.dist-info/WHEEL
pyautoattack-0.2.0.dist-info/METADATA
pyautoattack-0.2.0.dist-info/RECORD
