Metadata-Version: 2.1
Name: pyautoattack
Version: 0.2.0
Summary: Reliable evaluation of adversarial robustness with an ensemble of diverse parameter-free attacks
Author: Francesco Croce, Matthias Hein
Requires-Python: ~=3.9
Classifier: License :: OSI Approved :: MIT License
Project-URL: Homepage, https://github.com/fra31/auto-attack
